clioexlsx/__init__.py
clioexlsx/compare_wb.py
clioexlsx/compare_ws.py
clioexlsx-2.1.dist-info/LICENSE
clioexlsx-2.1.dist-info/METADATA
clioexlsx-2.1.dist-info/WHEEL
clioexlsx-2.1.dist-info/top_level.txt
clioexlsx-2.1.dist-info/RECORD
