Metadata-Version: 2.1
Name: clioexlsx
Version: 2.1
Summary: Compare worksheet or workbook, then highlight the different rows or cells on book 2 and then generate the output file. This module uses Pandas and XLWings
Home-page: UNKNOWN
Author: Cheny Lioe
Author-email: chenylioe@yahoo.com
License: UNKNOWN
Keywords: xlsx,compare excel
Platform: UNKNOWN
License-File: LICENSE
